llama_index/packs/auto_merging_retriever/__init__.py
llama_index/packs/auto_merging_retriever/base.py
llama_index_packs_auto_merging_retriever-0.5.1.dist-info/METADATA
llama_index_packs_auto_merging_retriever-0.5.1.dist-info/WHEEL
llama_index_packs_auto_merging_retriever-0.5.1.dist-info/licenses/LICENSE
llama_index_packs_auto_merging_retriever-0.5.1.dist-info/RECORD
