Metadata-Version: 2.4
Name: llama-index-packs-auto-merging-retriever
Version: 0.5.1
Summary: llama-index packs auto_merging_retriever integration
Author-email: Your Name <you@example.com>
Maintainer: jerryjliu
License-Expression: MIT
License-File: LICENSE
Keywords: auto,automerging,index,merging,retriever
Requires-Python: <4.0,>=3.9
Requires-Dist: llama-index-core<0.15,>=0.13.0
